README.md
setup.py
wordrank/__init__.py
wordrank/__main__.py
wordrank/config.py
wordrank/feature.py
wordrank/model.py
wordrank/version.py
wordrank/wordrank.py
wordrank.egg-info/PKG-INFO
wordrank.egg-info/SOURCES.txt
wordrank.egg-info/dependency_links.txt
wordrank.egg-info/not-zip-safe
wordrank.egg-info/requires.txt
wordrank.egg-info/top_level.txt
wordrank/../extra_data/classify_model.pkl
wordrank/../extra_data/entropy_word_score.json
wordrank/../extra_data/pmi_word_score.json
wordrank/../extra_data/test.csv
wordrank/../extra_data/train.csv
wordrank/data/common_char_set.txt
wordrank/data/person_name.txt
wordrank/data/place_name.txt
wordrank/data/stopwords.txt
wordrank/features/__init__.py
wordrank/features/language_feature.py
wordrank/features/pmi.py
wordrank/features/statistics_feature.py
wordrank/features/text_feature.py
wordrank/features/textrank.py
wordrank/features/tfidf.py
wordrank/utils/__init__.py
wordrank/utils/io_utils.py
wordrank/utils/logger.py
wordrank/utils/text_utils.py
wordrank/utils/tokenizer.py